slugify-stubs/METADATA.toml
slugify-stubs/__init__.pyi
slugify-stubs/__version__.pyi
slugify-stubs/slugify.pyi
slugify-stubs/special.pyi
types_python_slugify-8.0.2.20240127.dist-info/METADATA
types_python_slugify-8.0.2.20240127.dist-info/WHEEL
types_python_slugify-8.0.2.20240127.dist-info/top_level.txt
types_python_slugify-8.0.2.20240127.dist-info/RECORD
